{
  "footer_contact_address": "मुंबई, महाराष्ट्र",
  "footer_copyright": "© २०२५ आरोग्य सहायक. सर्व हक्क महाराष्ट्र शासनाकडे राखीव आहेत.",
  "district_reach_title": "आमची प्रादेशिक पोहोच",
  "district_reach_description": "ग्रामीण समुदायांपर्यंत आरोग्य सेवा पोहोचवण्यासाठी महाराष्ट्र आणि लगतच्या राज्यांमध्ये विस्तार करत आहोत.",
  "maharashtra_focus": "महाराष्ट्र लक्ष",
  "primary_coverage_area": "प्राथमिक कव्हरेज क्षेत्र",
  "view_detailed_coverage": "तपशीलवार कव्हरेज नकाशा पहा",
  "departments_partners_title": "विभाग आणि भागीदार",
  "view_all": "सर्व पहा",
  "regional_reach_title": "प्रादेशिक पोहोच",
  "interactive_map": "परस्परसंवादी नकाशा",
  "districts_of_maharashtra": "महाराष्ट्रातील जिल्हे",
  "konkan_division": "कोकण विभाग",
  "pune_division": "पुणे विभाग",
  "nashik_division": "नाशिक विभाग",
  "aurangabad_division": "औरंगाबाद विभाग",
  "amravati_division": "अमरावती विभाग",
  "nagpur_division": "नागपूर विभाग",
  "active": "सक्रिय",
  "planning": "नियोजन",
  "districts_covered": "जिल्हे समाविष्ट",
  "active_divisions": "सक्रिय विभाग",
  "click_to_view_detailed_coverage": "तपशीलवार जिल्हावार कव्हरेज पाहण्यासाठी क्लिक करा",
  "launch_map": "नकाशा सुरू करा",
  "language_switcher_label": "भाषा",
  "login_title": "लॉग इन",
  "role_patient": "रुग्ण",
  "role_health_worker": "आरोग्य कर्मचारी",
  "mobile_number_label": "मोबाइल नंबर",
  "enter_mobile_number_placeholder": "मोबाइल नंबर प्रविष्ट करा",
  "official_id_label": "अधिकृत आयडी",
  "enter_official_id_placeholder": "अधिकृत आयडी प्रविष्ट करा",
  "password_label": "पासवर्ड",
  "enter_password_placeholder": "पासवर्ड प्रविष्ट करा",
  "login_button": "लॉग इन करा",
  "forgot_password_link": "पासवर्ड विसरलात?",
  "no_account_question": "खाते नाहीये?",
  "register_link": "नोंदणी करा",
  "patient_registration_title": "रुग्ण नोंदणी",
  "step_indicator": "पायरी {step} पैकी {totalSteps}",
  "full_name_label": "पूर्ण नाव",
  "enter_full_name_placeholder": "पूर्ण नाव प्रविष्ट करा",
  "next_step_button": "पुढील पायरी",
  "otp_label": "ओटीपी",
  "enter_otp_placeholder": "ओटीपी प्रविष्ट करा",
  "create_password_placeholder": "पासवर्ड तयार करा",
  "confirm_password_label": "पासवर्डची पुष्टी करा",
  "confirm_password_placeholder": "पासवर्डची पुष्टी करा",
  "preferred_language_label": "पसंतीची भाषा",
  "select_language_placeholder": "भाषा निवडा",
  "agree_to_terms": "मी अटी व शर्तींना सहमत आहे",
  "terms_of_service_link": "सेवा अटी",
  "register_button": "नोंदणी करा",
  "previous_step_button": "मागील पायरी",
  "password_mismatch_error": "पासवर्ड जुळत नाही.",
  "patient_registration_success": "रुग्णाची यशस्वीरित्या नोंदणी झाली.",
  "health_worker_registration_title": "आरोग्य कर्मचारी नोंदणी",
  "health_worker_registration_message_part1": "जर तुम्ही मान्यताप्राप्त आरोग्य कर्मचारी असाल,",
  "health_worker_registration_message_part2": "तर कृपया खाते तयार करण्यासाठी तुमच्या प्रादेशिक व्यवस्थापकाशी संपर्क साधा.",
  "empty_fields_error": "कृपया सर्व आवश्यक फील्ड भरा.",
  "login_successful": "लॉग इन यशस्वी झाले.",
  "invalid_mobile_number_error": "कृपया वैध मोबाइल नंबर प्रविष्ट करा (उदा. १० अंक).",
  "otp_sent_success": "ओटीपी यशस्वीरित्या पाठवला गेला.",
  "password_strength_error": "पासवर्ड किमान ६ वर्णांचा असावा.",
  "agree_to_terms_error": "नोंदणी करण्यासाठी तुम्हाला अटी व शर्तींना सहमत असणे आवश्यक आहे.",
  "welcome_patient": "स्वागत आहे, {patientName}! तुमचा आरोग्य प्रवास, येथेच.",
  "vitals_pulse_title": "महत्वाची माहिती",
  "blood_sugar_label": "रक्तातील साखर",
  "last_logged": "↓ शेवटची नोंद: {time}",
  "great_job_in_range": "उत्तम! तुमची रीडिंग श्रेणीत आहे.",
  "blood_pressure_label": "रक्तदाब",
  "weight_label": "वजन",
  "progress_journey_title": "प्रगतीचा प्रवास",
  "select_vital_placeholder": "महत्वाचे निवडा",
  "select_time_period_placeholder": "वेळ कालावधी निवडा",
  "last_7_days": "गेले ७ दिवस",
  "last_30_days": "गेले ३० दिवस",
  "last_90_days": "गेले ९० दिवस",
  "target_zone_label": "लक्ष्य क्षेत्र: {range}",
  "health_rituals_title": "आजचे आरोग्य विधी",
  "take_medication_task": "औषध घ्या ({time})",
  "log_blood_sugar_task": "रक्तातील साखर नोंदवा",
  "walk_task": "{minutes} मिनिटांची चाल",
  "health_story_title": "वैयक्तिक आरोग्य कथा",
  "recipe_title_1": "शुगर-फ्री आहारासाठी ३ सोप्या पाककृती",
  "yoga_title_1": "रक्तदाबासाठी ५ सोपी योगासने",
  "diet_plan_title_1": "मधुमेह व्यवस्थापनासाठी आवश्यक आहार योजना",
  "log_new_vitals_button": "नवीन महत्वाची माहिती नोंदवा",
  "welcome_health_worker": "स्वागत आहे, {healthWorkerName}! तुमचे डॅशबोर्ड.",
  "key_metrics_title": "प्रमुख मेट्रिक्स",
  "total_patients_label": "एकूण रुग्ण",
  "active_campaigns_label": "सक्रिय मोहिमा",
  "health_centers_label": "आरोग्य केंद्रे",
  "districts_covered_label": "समाविष्ट जिल्हे",
  "regional_overview_title": "प्रादेशिक विहंगावलोकन",
  "patients_count_label": "रुग्ण",
  "health_workers_count_label": "आरोग्य कर्मचारी",
  "action_items_title": "कृती आयटम आणि घोषणा",
  "no_action_items_message": "सध्या कोणतेही नवीन कृती आयटम किंवा घोषणा नाहीत.",
  "choose_registration_type": "तुमच्या नोंदणीचा प्रकार निवडा",
  "register_as_patient_button": "रुग्ण म्हणून नोंदणी करा",
  "register_as_health_worker_button": "आरोग्य कर्मचारी म्हणून नोंदणी करा"
}
